{"_id":{"$oid":"5b121e92d059ae04dbead4e0"},"name":"Julian Martinez Barron","rfc":"MABJ840414593","cellphone":"8118075176","jobs":[],"create_date":"2018-06-02T04:35:30.696Z","update_date":{"$date":"2019-02-08T15:36:45.509Z"},"desc":"Prueba","invoice":true,"invoiceInfo":true}
{"_id":{"$oid":"5b1328b8c07eb60c07e5a553"},"name":"Jesus Elizondo","contact":"","rfc":"","cellphone":"8117514835","phone":"","address":"Crispin Treviño #206","hood":"Huinala","county":"Apodaca","state":"Nuevo Leon","update_date":{"$date":"2018-06-25T03:44:06.292Z"},"desc":""}
{"_id":{"$oid":"5b955f7006502d23feef31e0"},"name":"Jorge Perez Alfaro","cellphone":"8118153333","address":"Mision de san jorge #150","hood":"Mision de huinala","county":"Apodaca","desc":"Tapizado de sala pre presupuesto $11,500\nVinil: Line Stone\nTela: Dark super grey\n+ 500 de patas","create_by":"5a9519b35649c476ca740a2d","create_date":"2018-09-09T17:59:12.388Z","update_date":{"$date":"2018-09-15T02:32:56.975Z"},"visited":false,"rfc":""}
{"_id":{"$oid":"5bf4fb2a7d61393fb15f0ebb"},"name":"Edgar valli","contact":"","rfc":"","cellphone":"8121476458","phone":"14931696","address":"Rio Moctezuma 139","hood":"Pueblo Nuevo","county":"Apodaca","state":"Nuevo Leon","description":"","update_date":{"$date":"2019-02-08T15:24:02.126Z"},"country":"Mexico","zip":"66646"}
{"_id":{"$oid":"5c435c738b705f60d3f2e8bd"},"name":"Lorena Ruiz","contact":"","rfc":"","cellphone":"8126892387","phone":"","address":"Tomatlan 341","hood":"Noria Sur","county":"Apodaca","state":"Nuevo Leon","description":"","create_by":"5a9519b35649c476ca740a2d","create_date":{"$date":"2019-01-19T17:20:51.666Z"},"update_date":{"$date":"2019-01-20T15:17:35.931Z"}}
{"_id":{"$oid":"5c435cae8b705f60d3f2e8be"},"name":"Maria Cristina","contact":"","rfc":"","cellphone":"83413280","phone":"","address":"Tizapan 224","hood":"Noria Sur","county":"Apodaca","state":"Nuevo Leon","description":"","create_by":"5a9519b35649c476ca740a2d","create_date":{"$date":"2019-01-19T17:21:50.237Z"},"update_date":{"$date":"2019-01-20T15:16:44.388Z"}}
{"_id":{"$oid":"5c7170d05d4a1006ef81edcb"},"name":"Janeth Sala sofacama","cellphone":"8186585309","address":"Coruña 106","hood":"Triana","county":"Apodaca","state":"Nuevo Leon","country":"Mexico","zip":"66606","createBy":"5a9519b35649c476ca740a2d","createDate":"2019-02-23T16:12:00.467Z","updateDate":{"$date":"2019-04-02T04:02:30.039Z"}}
